utilsbox/__init__.py
utilsbox/consts.py
utilsbox/custom.py
utilsbox/plotting.py
utilsbox/preprocessing.py
utilsbox/utils.py
utilsbox-0.0.27.dist-info/METADATA
utilsbox-0.0.27.dist-info/WHEEL
utilsbox-0.0.27.dist-info/top_level.txt
utilsbox-0.0.27.dist-info/RECORD
