Metadata-Version: 2.1
Name: utilsbox
Version: 0.0.27
Summary: Contains useful functions and classes
Author: Vikas Sanwal
Author-email: <vikassnwl@gmail.com>
Keywords: python
Classifier: Development Status :: 1 - Planning
Classifier: Intended Audience :: Developers
Classifier: Programming Language :: Python :: 3
Classifier: Operating System :: Unix
Classifier: Operating System :: MacOS :: MacOS X
Classifier: Operating System :: Microsoft :: Windows
Requires-Dist: absl-py==2.1.0
Requires-Dist: asttokens==3.0.0
Requires-Dist: astunparse==1.6.3
Requires-Dist: azure-core==1.32.0
Requires-Dist: azure-storage-blob==12.24.0
Requires-Dist: beautifulsoup4==4.12.3
Requires-Dist: boto3==1.35.81
Requires-Dist: botocore==1.35.81
Requires-Dist: cachetools==5.5.0
Requires-Dist: certifi==2024.12.14
Requires-Dist: cffi==1.17.1
Requires-Dist: charset-normalizer==3.4.0
Requires-Dist: comm==0.2.2
Requires-Dist: contourpy==1.3.1
Requires-Dist: cryptography==44.0.0
Requires-Dist: cycler==0.12.1
Requires-Dist: debugpy==1.8.11
Requires-Dist: decorator==5.1.1
Requires-Dist: exceptiongroup==1.2.2
Requires-Dist: executing==2.1.0
Requires-Dist: filelock==3.16.1
Requires-Dist: flatbuffers==24.3.25
Requires-Dist: fonttools==4.55.3
Requires-Dist: gast==0.6.0
Requires-Dist: gdown==5.2.0
Requires-Dist: google-api-core==2.24.0
Requires-Dist: google-auth==2.37.0
Requires-Dist: google-cloud-core==2.4.1
Requires-Dist: google-cloud-storage==2.19.0
Requires-Dist: google-crc32c==1.6.0
Requires-Dist: google-pasta==0.2.0
Requires-Dist: google-resumable-media==2.7.2
Requires-Dist: googleapis-common-protos==1.66.0
Requires-Dist: grpcio==1.68.1
Requires-Dist: h5py==3.12.1
Requires-Dist: idna==3.10
Requires-Dist: ipykernel==6.29.5
Requires-Dist: ipython==8.30.0
Requires-Dist: isodate==0.7.2
Requires-Dist: jedi==0.19.2
Requires-Dist: jmespath==1.0.1
Requires-Dist: jupyter-client==8.6.3
Requires-Dist: jupyter-core==5.7.2
Requires-Dist: keras==3.7.0
Requires-Dist: kiwisolver==1.4.7
Requires-Dist: libclang==18.1.1
Requires-Dist: Markdown==3.7
Requires-Dist: markdown-it-py==3.0.0
Requires-Dist: MarkupSafe==3.0.2
Requires-Dist: matplotlib==3.10.0
Requires-Dist: matplotlib-inline==0.1.7
Requires-Dist: mdurl==0.1.2
Requires-Dist: ml-dtypes==0.4.1
Requires-Dist: namex==0.0.8
Requires-Dist: nest-asyncio==1.6.0
Requires-Dist: numpy==2.0.2
Requires-Dist: opencv-python==4.10.0.84
Requires-Dist: opt-einsum==3.4.0
Requires-Dist: optree==0.13.1
Requires-Dist: packaging==24.2
Requires-Dist: pandas==2.2.3
Requires-Dist: parso==0.8.4
Requires-Dist: pexpect==4.9.0
Requires-Dist: pillow==11.0.0
Requires-Dist: platformdirs==4.3.6
Requires-Dist: prompt-toolkit==3.0.48
Requires-Dist: proto-plus==1.25.0
Requires-Dist: protobuf==5.29.1
Requires-Dist: psutil==6.1.0
Requires-Dist: ptyprocess==0.7.0
Requires-Dist: pure-eval==0.2.3
Requires-Dist: pyasn1==0.6.1
Requires-Dist: pyasn1-modules==0.4.1
Requires-Dist: pycparser==2.22
Requires-Dist: Pygments==2.18.0
Requires-Dist: pyparsing==3.2.0
Requires-Dist: PySocks==1.7.1
Requires-Dist: python-dateutil==2.9.0.post0
Requires-Dist: pytz==2024.2
Requires-Dist: pyzmq==26.2.0
Requires-Dist: requests==2.32.3
Requires-Dist: rich==13.9.4
Requires-Dist: rsa==4.9
Requires-Dist: s3transfer==0.10.4
Requires-Dist: scipy==1.14.1
Requires-Dist: six==1.17.0
Requires-Dist: soupsieve==2.6
Requires-Dist: stack-data==0.6.3
Requires-Dist: tensorboard==2.18.0
Requires-Dist: tensorboard-data-server==0.7.2
Requires-Dist: tensorflow==2.18.0
Requires-Dist: tensorflow-io-gcs-filesystem==0.37.1
Requires-Dist: termcolor==2.5.0
Requires-Dist: tornado==6.4.2
Requires-Dist: tqdm==4.67.1
Requires-Dist: traitlets==5.14.3
Requires-Dist: typing-extensions==4.12.2
Requires-Dist: tzdata==2024.2
Requires-Dist: urllib3==2.2.3
Requires-Dist: wcwidth==0.2.13
Requires-Dist: Werkzeug==3.1.3
Requires-Dist: wrapt==1.17.0
